tripleo_common/__init__.py
tripleo_common/arch.py
tripleo_common/constants.py
tripleo_common/exception.py
tripleo_common/i18n.py
tripleo_common/inventories.py
tripleo_common/inventory.py
tripleo_common/update.py
tripleo_common/filters/__init__.py
tripleo_common/filters/capabilities_filter.py
tripleo_common/filters/list.py
tripleo_common/image/__init__.py
tripleo_common/image/base.py
tripleo_common/image/build.py
tripleo_common/image/exception.py
tripleo_common/image/image_builder.py
tripleo_common/image/image_export.py
tripleo_common/image/image_uploader.py
tripleo_common/image/kolla_builder.py
tripleo_common/image/builder/__init__.py
tripleo_common/image/builder/base.py
tripleo_common/image/builder/buildah.py
tripleo_common/releasenotes/notes/automatically-retry-failed-deployments-baf0c701e6d1ad4a.yaml
tripleo_common/releasenotes/notes/convert-docker-params-84dfc6083e88bb52.yaml
tripleo_common/templates/deployment.j2
tripleo_common/templates/deployments.yaml
tripleo_common/templates/heat-config.j2
tripleo_common/templates/host_var_server.j2
tripleo_common/tests/__init__.py
tripleo_common/tests/base.py
tripleo_common/tests/test_arch.py
tripleo_common/tests/test_filters.py
tripleo_common/tests/test_inventories.py
tripleo_common/tests/test_inventory.py
tripleo_common/tests/test_update.py
tripleo_common/tests/fake_config/__init__.py
tripleo_common/tests/fake_config/fakes.py
tripleo_common/tests/fake_neutron/__init__.py
tripleo_common/tests/fake_neutron/fakes.py
tripleo_common/tests/fake_neutron/stubs.py
tripleo_common/tests/fake_nova/README
tripleo_common/tests/fake_nova/__init__.py
tripleo_common/tests/fake_nova/scheduler/__init__.py
tripleo_common/tests/fake_nova/scheduler/filters.py
tripleo_common/tests/image/__init__.py
tripleo_common/tests/image/fakes.py
tripleo_common/tests/image/test_base.py
tripleo_common/tests/image/test_build.py
tripleo_common/tests/image/test_image_builder.py
tripleo_common/tests/image/test_image_export.py
tripleo_common-18.0.0.dist-info/AUTHORS
tripleo_common-18.0.0.dist-info/LICENSE
tripleo_common-18.0.0.dist-info/METADATA
tripleo_common-18.0.0.dist-info/WHEEL
tripleo_common-18.0.0.dist-info/pbr.json
tripleo_common-18.0.0.dist-info/top_level.txt
tripleo_common-18.0.0.dist-info/RECORD
