Metadata-Version: 2.1
Name: tripleo-common
Version: 18.0.0
Summary: A common library for TripleO workflows.
Home-page: https://docs.openstack.org/tripleo-common/latest/
Author: OpenStack
Author-email: openstack-discuss@lists.openstack.org
License: UNKNOWN
Platform: UNKNOWN
Classifier: Environment :: OpenStack
Classifier: Intended Audience :: Information Technology
Classifier: Intended Audience :: System Administrators
Classifier: License :: OSI Approved :: Apache Software License
Classifier: Operating System :: POSIX :: Linux
Classifier: Programming Language :: Python
Classifier: Programming Language :: Python :: Implementation :: CPython
Classifier: Programming Language :: Python :: 3 :: Only
Classifier: Programming Language :: Python :: 3
Classifier: Programming Language :: Python :: 3.8
Classifier: Programming Language :: Python :: 3.9
Requires-Python: >=3.8
Requires-Dist: GitPython (>=1.0.1)
Requires-Dist: Jinja2 (>=2.10)
Requires-Dist: PyYAML (>=3.12)
Requires-Dist: cryptography (>=3.4.7)
Requires-Dist: metalsmith (>=0.13.0)
Requires-Dist: oslo.concurrency (>=3.26.0)
Requires-Dist: oslo.config (>=5.2.0)
Requires-Dist: oslo.log (>=3.36.0)
Requires-Dist: oslo.utils (>=3.33.0)
Requires-Dist: passlib (>=1.7.0)
Requires-Dist: pbr (!=2.1.0,>=2.0.0)
Requires-Dist: python-heatclient (>=1.10.0)
Requires-Dist: python-ironicclient (!=2.5.2,!=2.7.1,!=3.0.0,>=2.3.0)
Requires-Dist: requests (!=2.20.0,>=2.18.0)
Requires-Dist: tenacity (>=6.1.0)
